examples/__init__.py
examples/base_score.py
examples/pdme_arena.py
examples/pdme_coding_demo.py
examples/utils.py
opti_pdme/__init__.py
opti_pdme/model_utils.py
opti_pdme/opticonomy_pdme.py
pdme/__init__.py
pdme/evaluate.py
pdme/generate_bootstrap_prompts.py
opticonomy_pdme-0.1.19.dist-info/LICENSE
opticonomy_pdme-0.1.19.dist-info/METADATA
opticonomy_pdme-0.1.19.dist-info/WHEEL
opticonomy_pdme-0.1.19.dist-info/entry_points.txt
opticonomy_pdme-0.1.19.dist-info/top_level.txt
opticonomy_pdme-0.1.19.dist-info/RECORD
