Metadata-Version: 2.1
Name: opticonomy-pdme
Version: 0.1.19
Summary: Opticonomy Prompt Driven Model Evaluation (PDME)
Home-page: https://github.com/opticonomy/opticonomy-pdme
Author: Opticonomy
Author-email: info@opticonomy.com
License: UNKNOWN
Platform: UNKNOWN
Classifier: Programming Language :: Python :: 3
Classifier: License :: OSI Approved :: MIT License
Classifier: Operating System :: OS Independent
Requires-Python: >=3.6
License-File: LICENSE
